[
  {
    "date": "9/16/2025",
    "order_number": "25090284917811",
    "sellerorderno": "CU25090273122125",
    "payment_method": "SEB_COF",
    "card_number": "486146******4094",
    "amount": "658.00",
    "wallet_number": "",
    "wallet_number_normalized": "",
    "transaction_id": "",
    "cashback": "",
    "date_fmt": "16 Sep 2025",
    "order_number_norm": "25090284917811",
    "sellerorderno_norm": "CU25090273122125",
    "transaction_id_norm": "",
    "source": "SEBL"
  },
  {
    "date": "9/16/2025",
    "order_number": "25090753514564",
    "sellerorderno": "CU25090761666400-1",
    "payment_method": "SEB_COF",
    "card_number": "537682******7238",
    "amount": "359.52",
    "wallet_number": "",
    "wallet_number_normalized": "",
    "transaction_id": "",
    "cashback": "",
    "date_fmt": "16 Sep 2025",
    "order_number_norm": "25090753514564",
    "sellerorderno_norm": "CU25090761666400-1",
    "transaction_id_norm": "",
    "source": "SEBL"
  },
  {
    "date": "9/16/2025",
    "order_number": "25090276006316",
    "sellerorderno": "CU25090250728222",
    "payment_method": "SEB_COF",
    "card_number": "486145******9633",
    "amount": "767.00",
    "wallet_number": "",
    "wallet_number_normalized": "",
    "transaction_id": "",
    "cashback": "",
    "date_fmt": "16 Sep 2025",
    "order_number_norm": "25090276006316",
    "sellerorderno_norm": "CU25090250728222",
    "transaction_id_norm": "",
    "source": "SEBL"
  },
  {
    "date": "9/17/2025",
    "order_number": "25090753514564",
    "sellerorderno": "CU25090764889615-3",
    "payment_method": "SEB_COF",
    "card_number": "537682******7238",
    "amount": "313.92",
    "wallet_number": "",
    "wallet_number_normalized": "",
    "transaction_id": "",
    "cashback": "",
    "date_fmt": "17 Sep 2025",
    "order_number_norm": "25090753514564",
    "sellerorderno_norm": "CU25090764889615-3",
    "transaction_id_norm": "",
    "source": "SEBL"
  }
]